{
 "actions": [],
 "creation": "2021-09-18 09:36:14.776607",
 "doctype": "DocType",
 "engine": "InnoDB",
 "field_order": [
  "rule",
  "coa",
  "coa_lawan",
  "column_break_gafph",
  "nama_leasing",
  "nominal",
  "tertagih"
 ],
 "fields": [
  {
   "fieldname": "coa",
   "fieldtype": "Link",
   "in_list_view": 1,
   "label": "COA",
   "options": "Account",
   "read_only": 1
  },
  {
   "fieldname": "nominal",
   "fieldtype": "Currency",
   "in_list_view": 1,
   "label": "Nominal",
   "read_only_depends_on": "eval:!parent.ignore_rule_discount"
  },
  {
   "fieldname": "nama_leasing",
   "fieldtype": "Link",
   "in_list_view": 1,
   "label": "Nama Leasing",
   "options": "Customer",
   "read_only": 1
  },
  {
   "default": "0",
   "fieldname": "tertagih",
   "fieldtype": "Check",
   "label": "Tertagih",
   "no_copy": 1,
   "read_only": 1
  },
  {
   "fieldname": "rule",
   "fieldtype": "Data",
   "in_list_view": 1,
   "label": "Rule",
   "read_only": 1
  },
  {
   "fieldname": "coa_lawan",
   "fieldtype": "Link",
   "label": "COA Lawan",
   "options": "Account"
  },
  {
   "fieldname": "column_break_gafph",
   "fieldtype": "Column Break"
  }
 ],
 "index_web_pages_for_search": 1,
 "istable": 1,
 "links": [],
 "modified": "2024-03-21 08:24:15.557272",
 "modified_by": "Administrator",
 "module": "wongkar_selling",
 "name": "Table Disc Leasing",
 "owner": "Administrator",
 "permissions": [],
 "sort_field": "modified",
 "sort_order": "DESC",
 "track_changes": 1
}